README.md
setup.py
rater/__init__.py
rater.egg-info/PKG-INFO
rater.egg-info/SOURCES.txt
rater.egg-info/dependency_links.txt
rater.egg-info/requires.txt
rater.egg-info/top_level.txt
rater/../LICENSE
rater/../README.md
rater/../requirements.txt
rater/datasets/__init__.py
rater/datasets/criteo.py
rater/datasets/movielens.py
rater/layers/__init__.py
rater/layers/activation.py
rater/layers/core.py
rater/layers/inputs.py
rater/layers/interaction.py
rater/layers/sequence.py
rater/layers/utils.py
rater/metrics/__init__.py
rater/metrics/ranking.py
rater/metrics/rating.py
rater/models/__init__.py
rater/models/afm.py
rater/models/als.py
rater/models/base.py
rater/models/basemodel.py
rater/models/bpmf.py
rater/models/dcn.py
rater/models/deepfm.py
rater/models/din.py
rater/models/fnn.py
rater/models/lfm.py
rater/models/nfm.py
rater/models/pnn.py
rater/models/usercf.py
rater/utils/__init__.py
rater/utils/get_file.py
rater/utils/logger.py
rater/utils/validation.py