Metadata-Version: 2.1
Name: rater
Version: 0.1.1
Summary: rater
Home-page: https://github.com/shibing624/rater
Author: XuMing
Author-email: xuming624@qq.com
License: Apache License 2.0
Keywords: rater,recommender,Recommendation System,recommendation model
Platform: UNKNOWN
Classifier: Intended Audience :: Developers
Classifier: Operating System :: OS Independent
Classifier: Natural Language :: Chinese (Simplified)
Classifier: Natural Language :: Chinese (Traditional)
Classifier: Programming Language :: Python
Classifier: Programming Language :: Python :: 3
Classifier: Programming Language :: Python :: 3.5
Classifier: Programming Language :: Python :: 3.6
Classifier: Programming Language :: Python :: 3.7
Classifier: Topic :: Text Processing
Classifier: Topic :: Text Processing :: Indexing
Classifier: Topic :: Text Processing :: Linguistic
